{
  "success": true,
  "returnCode": "1001",
  "returnMessage": null,
  "data": {
    "total": 33736,
    "title": "wap图墙",
    "sort": "pop",
    "isEnd": false,
    "cpc_offset": 0,
    "param": {
      "ptpWallDoc": "_wall_docs",
      "_mgjuuid": "5c0094cf-a7e1-45dc-bc36-dedf0cf6d0ed",
      "sort": "pop",
      "eventId": 70003,
      "cpc_offset": 0,
      "page": "1",
      "cKey": "wap-search",
      "cpcEventId": 70005,
      "ptpWallCpc": "_wall_cpc",
      "ptpPartC": "_mb_mls_0_wap-search_noab-noab",
      "section": "0",
      "minPrice": "5"
    },
    "page": 1,
    "list": [
      {
        "orgPrice": "￥495.00",
        "acm": "3.ms.2_4_1gpsjro.0.8239-25176.05NORqhIsBsQq.t_0-lc_17",
        "iid": "1gpsjro",
        "link": "http://item.meilishuo.com/h5/detail/1gpsjro?acm=3.ms.2_4_1gpsjro.0.8239-25176.05NORqhIsBsQq.t_0-lc_17",
        "clientUrl": "http://item.meilishuo.com/h5/detail/1gpsjro?acm=3.ms.2_4_1gpsjro.0.8239-25176.05NORqhIsBsQq.t_0-lc_17",
        "itemType": 1,
        "popularStar": null,
        "cparam": null,
        "itemMarks": "98 107",
        "show": {
          "w": 320,
          "img": "http://s2.mogucdn.com/p2/161017/1339505863_33fk4c872j080c1il2d91ie0l0084_640x960.jpg_320x999.jpg",
          "h": 416
        },
        "type": 2,
        "sale": 10,
        "title": "包包春夏新款女包斜挎包徽章百搭小香风菱格链条包勋章女士单肩包",
        "cfav": 545,
        "price": "￥99.00",
        "ptpC": "_mb_mls_0_wap-search_noab-noab",
        "lefttop_taglist": [
          {
            "img": "http://s18.mogucdn.com/b7/avatar/160520/1y0mpt_ie4tqodbgrrdcnlbhazdambqgqyde_50x54.jpg",
            "w": 50,
            "h": 54
          }
        ],
        "showLarge": {
          "img": "http://s2.mogucdn.com/p2/161017/1339505863_33fk4c872j080c1il2d91ie0l0084_640x960.jpg_560x999.jpg",
          "w": 560,
          "h": 840
        },
        "leftbottom_taglist": []
      },
      {
        "orgPrice": "￥495.00",
        "acm": "3.ms.2_4_1k9rliu.0.8239-25176.05NORqhIsBsQq.t_0-lc_17",
        "iid": "1k9rliu",
        "link": "http://item.meilishuo.com/h5/detail/1k9rliu?acm=3.ms.2_4_1k9rliu.0.8239-25176.05NORqhIsBsQq.t_0-lc_17",
        "clientUrl": "http://item.meilishuo.com/h5/detail/1k9rliu?acm=3.ms.2_4_1k9rliu.0.8239-25176.05NORqhIsBsQq.t_0-lc_17",
        "itemType": 1,
        "popularStar": null,
        "cparam": null,
        "itemMarks": "",
        "show": {
          "w": 320,
          "img": "http://s2.mogucdn.com/mlcdn/c45406/170407_613eb31l7lld3l66894le062lid66_640x960.jpg_320x999.jpg",
          "h": 416
        },
        "type": 2,
        "sale": 0,
        "title": "新款单肩时尚斜挎包刘雯同款女包小包包豆腐包链条锁扣小方包",
        "cfav": 0,
        "price": "￥99.00",
        "ptpC": "_mb_mls_0_wap-search_noab-noab",
        "lefttop_taglist": [
          {
            "img": "http://s18.mogucdn.com/b7/avatar/160520/1y0mpt_ie4tqodbgrrdcnlbhazdambqgqyde_50x54.jpg",
            "w": 50,
            "h": 54
          }
        ],
        "showLarge": {
          "img": "http://s2.mogucdn.com/mlcdn/c45406/170407_613eb31l7lld3l66894le062lid66_640x960.jpg_560x999.jpg",
          "w": 560,
          "h": 840
        },
        "leftbottom_taglist": []
      },
      {
        "orgPrice": "￥197.00",
        "acm": "3.ms.2_4_1glrl08.0.8239-25176.05NORqhIsBsQq.t_0-lc_17",
        "iid": "1glrl08",
        "link": "http://item.meilishuo.com/h5/detail/1glrl08?acm=3.ms.2_4_1glrl08.0.8239-25176.05NORqhIsBsQq.t_0-lc_17",
        "clientUrl": "http://item.meilishuo.com/h5/detail/1glrl08?acm=3.ms.2_4_1glrl08.0.8239-25176.05NORqhIsBsQq.t_0-lc_17",
        "itemType": 1,
        "popularStar": null,
        "cparam": null,
        "itemMarks": "98 107",
        "show": {
          "w": 320,
          "img": "http://s2.mogucdn.com/p2/160815/869099060_4f8h7efkhlajg3f8afl4li7k5ajbb_640x960.jpg_320x999.jpg",
          "h": 416
        },
        "type": 2,
        "sale": 0,
        "title": "不莱玫新款时尚韩版手机包 女式单肩斜挎包小包包 迷你小方包",
        "cfav": 39,
        "price": "￥137.90",
        "ptpC": "_mb_mls_0_wap-search_noab-noab",
        "lefttop_taglist": [
          {
            "img": "http://s18.mogucdn.com/b7/avatar/160520/1y0mpt_ie4tqodbgrrdcnlbhazdambqgqyde_50x54.jpg",
            "w": 50,
            "h": 54
          }
        ],
        "showLarge": {
          "img": "http://s2.mogucdn.com/p2/160815/869099060_4f8h7efkhlajg3f8afl4li7k5ajbb_640x960.jpg_560x999.jpg",
          "w": 560,
          "h": 840
        },
        "leftbottom_taglist": []
      },
      {
        "orgPrice": "￥52.50",
        "acm": "3.ms.2_4_1kaosga.0.24470-25176.05NORqhIsBsQq.t_0-lc_17",
        "iid": "1kaosga",
        "link": "http://item.meilishuo.com/h5/detail/1kaosga?acm=3.ms.2_4_1kaosga.0.24470-25176.05NORqhIsBsQq.t_0-lc_17",
        "clientUrl": "http://item.meilishuo.com/h5/detail/1kaosga?acm=3.ms.2_4_1kaosga.0.24470-25176.05NORqhIsBsQq.t_0-lc_17",
        "itemType": 4,
        "popularStar": null,
        "cparam": null,
        "itemMarks": "135",
        "show": {
          "w": 320,
          "img": "http://s2.mogucdn.com/p2/170413/upload_4lk1i9h0iibgi57a33742hl7e36dg_640x900.jpg_320x999.jpg",
          "h": 416
        },
        "type": 2,
        "sale": 8,
        "title": "2017新款欢乐颂王子文曲筱绡同款包时尚小方包单肩斜挎小包包",
        "cfav": 373,
        "price": "￥52.50",
        "ptpC": "_mb_mls_0_wap-search_noab-noab",
        "lefttop_taglist": [],
        "showLarge": {
          "img": "http://s2.mogucdn.com/p2/170413/upload_4lk1i9h0iibgi57a33742hl7e36dg_640x900.jpg_560x999.jpg",
          "w": 560,
          "h": 788
        },
        "leftbottom_taglist": []
      },
      {
        "orgPrice": "￥179.90",
        "acm": "3.ms.2_1_1k9pzny.1.5865-25176.05NORqhIsBsQq.t_0-lc_17-c_1_17_194505355_0_1_0-c1_",
        "iid": "1k9pzny",
        "link": "http://item.meilishuo.com/h5/detail/1k9pzny?acm=3.ms.2_1_1k9pzny.1.5865-25176.05NORqhIsBsQq.t_0-lc_17-c_1_17_194505355_0_1_0-c1_&cparam=MTQ5MzAzNzM1OV8xNmZheHRpX2I0YjI2ODY1ZTA5NDJlOWZhZDg5M2EyOTY3MmU1ODczXzE3XzBfMTk0NTA1MzU1XzAuOTYzN18wXzFfMV8xMzVfMF8w",
        "clientUrl": "http://item.meilishuo.com/h5/detail/1k9pzny?acm=3.ms.2_1_1k9pzny.1.5865-25176.05NORqhIsBsQq.t_0-lc_17-c_1_17_194505355_0_1_0-c1_&cparam=MTQ5MzAzNzM1OV8xNmZheHRpX2I0YjI2ODY1ZTA5NDJlOWZhZDg5M2EyOTY3MmU1ODczXzE3XzBfMTk0NTA1MzU1XzAuOTYzN18wXzFfMV8xMzVfMF8w",
        "itemType": 3,
        "popularStar": null,
        "cparam": "MTQ5MzAzNzM1OV8xNmZheHRpX2I0YjI2ODY1ZTA5NDJlOWZhZDg5M2EyOTY3MmU1ODczXzE3XzBfMTk0NTA1MzU1XzAuOTYzN18wXzFfMV8xMzVfMF8w",
        "itemMarks": "",
        "show": {
          "w": 320,
          "img": "http://s2.mogucdn.com/mlcdn/c45406/170406_6315g5afdfhilk444a6baba6002ia_640x842.jpg_320x999.jpg",
          "h": 416
        },
        "type": 2,
        "sale": "10",
        "title": "新款女包潮欧美百搭单肩包简约刺绣口红医生包手提包斜挎包",
        "cfav": "35",
        "price": "￥89.95",
        "ptpC": "_mb_mls_0_wap-search_noab-noab",
        "lefttop_taglist": [],
        "showLarge": {
          "img": "http://s2.mogucdn.com/mlcdn/c45406/170406_6315g5afdfhilk444a6baba6002ia_640x842.jpg_560x999.jpg",
          "w": 560,
          "h": 737
        },
        "leftbottom_taglist": []
      },
      {
        "orgPrice": "￥179.90",
        "acm": "3.ms.2_1_1k9r14w.1.5865-25176.05NORqhIsBsQq.t_0-lc_17-c_1_17_194250815_0_2_0-c1_",
        "iid": "1k9r14w",
        "link": "http://item.meilishuo.com/h5/detail/1k9r14w?acm=3.ms.2_1_1k9r14w.1.5865-25176.05NORqhIsBsQq.t_0-lc_17-c_1_17_194250815_0_2_0-c1_&cparam=MTQ5MzAzNzM1OV8xNjFxYTVhX2UyN2I5ZDVmNTkwMGRmMTVmNWE4MjVmYjU4OWQ4YmQxXzE3XzFfMTk0MjUwODE1XzAuOTU3NV8wXzJfMV8xMzVfMF8w",
        "clientUrl": "http://item.meilishuo.com/h5/detail/1k9r14w?acm=3.ms.2_1_1k9r14w.1.5865-25176.05NORqhIsBsQq.t_0-lc_17-c_1_17_194250815_0_2_0-c1_&cparam=MTQ5MzAzNzM1OV8xNjFxYTVhX2UyN2I5ZDVmNTkwMGRmMTVmNWE4MjVmYjU4OWQ4YmQxXzE3XzFfMTk0MjUwODE1XzAuOTU3NV8wXzJfMV8xMzVfMF8w",
        "itemType": 3,
        "popularStar": null,
        "cparam": "MTQ5MzAzNzM1OV8xNjFxYTVhX2UyN2I5ZDVmNTkwMGRmMTVmNWE4MjVmYjU4OWQ4YmQxXzE3XzFfMTk0MjUwODE1XzAuOTU3NV8wXzJfMV8xMzVfMF8w",
        "itemMarks": "",
        "show": {
          "w": 320,
          "img": "http://s2.mogucdn.com/mlcdn/c45406/170407_2eh0dg2k699kcc22fhhk6kjg4gh4f_640x842.jpg_320x999.jpg",
          "h": 416
        },
        "type": 2,
        "sale": "4",
        "title": "女包2017新款休闲单肩包潮韩版链条包百搭斜挎包刺绣小方包",
        "cfav": "11",
        "price": "￥89.95",
        "ptpC": "_mb_mls_0_wap-search_noab-noab",
        "lefttop_taglist": [],
        "showLarge": {
          "img": "http://s2.mogucdn.com/mlcdn/c45406/170407_2eh0dg2k699kcc22fhhk6kjg4gh4f_640x842.jpg_560x999.jpg",
          "w": 560,
          "h": 737
        },
        "leftbottom_taglist": []
      },
      {
        "orgPrice": "￥50.00",
        "acm": "3.ms.2_4_1kaoswg.0.24470-25176.05NORqhIsBsQq.t_0-lc_17",
        "iid": "1kaoswg",
        "link": "http://item.meilishuo.com/h5/detail/1kaoswg?acm=3.ms.2_4_1kaoswg.0.24470-25176.05NORqhIsBsQq.t_0-lc_17",
        "clientUrl": "http://item.meilishuo.com/h5/detail/1kaoswg?acm=3.ms.2_4_1kaoswg.0.24470-25176.05NORqhIsBsQq.t_0-lc_17",
        "itemType": 4,
        "popularStar": null,
        "cparam": null,
        "itemMarks": "135",
        "show": {
          "w": 320,
          "img": "http://s2.mogucdn.com/p2/170413/upload_38f3e31gjckfb921cklgg6c6gdehg_640x900.jpg_320x999.jpg",
          "h": 416
        },
        "type": 2,
        "sale": 0,
        "title": "夏季小清新迷你锁扣小方包包2017新款潮简约单肩包百搭斜挎包",
        "cfav": 234,
        "price": "￥50.00",
        "ptpC": "_mb_mls_0_wap-search_noab-noab",
        "lefttop_taglist": [],
        "showLarge": {
          "img": "http://s2.mogucdn.com/p2/170413/upload_38f3e31gjckfb921cklgg6c6gdehg_640x900.jpg_560x999.jpg",
          "w": 560,
          "h": 788
        },
        "leftbottom_taglist": []
      },
      {
        "orgPrice": "￥137.50",
        "acm": "3.ms.2_4_1kapvfi.0.24470-25176.05NORqhIsBsQq.t_0-lc_17",
        "iid": "1kapvfi",
        "link": "http://item.meilishuo.com/h5/detail/1kapvfi?acm=3.ms.2_4_1kapvfi.0.24470-25176.05NORqhIsBsQq.t_0-lc_17",
        "clientUrl": "http://item.meilishuo.com/h5/detail/1kapvfi?acm=3.ms.2_4_1kapvfi.0.24470-25176.05NORqhIsBsQq.t_0-lc_17",
        "itemType": 4,
        "popularStar": null,
        "cparam": null,
        "itemMarks": "135",
        "show": {
          "w": 320,
          "img": "http://s2.mogucdn.com/p2/170419/upload_06bek87i4fca11af6a96l218gl166_640x900.jpg_320x999.jpg",
          "h": 416
        },
        "type": 2,
        "sale": 0,
        "title": "撞色小方包包女2017新款镶钻单肩包时尚链条包",
        "cfav": 427,
        "price": "￥137.50",
        "ptpC": "_mb_mls_0_wap-search_noab-noab",
        "lefttop_taglist": [],
        "showLarge": {
          "img": "http://s2.mogucdn.com/p2/170419/upload_06bek87i4fca11af6a96l218gl166_640x900.jpg_560x999.jpg",
          "w": 560,
          "h": 788
        },
        "leftbottom_taglist": []
      },
      {
        "orgPrice": "￥116.25",
        "acm": "3.ms.2_4_1h3d1li.0.24470-25176.05NORqhIsBsQq.t_0-lc_17",
        "iid": "1h3d1li",
        "link": "http://item.meilishuo.com/h5/detail/1h3d1li?acm=3.ms.2_4_1h3d1li.0.24470-25176.05NORqhIsBsQq.t_0-lc_17",
        "clientUrl": "http://item.meilishuo.com/h5/detail/1h3d1li?acm=3.ms.2_4_1h3d1li.0.24470-25176.05NORqhIsBsQq.t_0-lc_17",
        "itemType": 4,
        "popularStar": null,
        "cparam": null,
        "itemMarks": "135 107",
        "show": {
          "w": 320,
          "img": "http://s2.mogucdn.com/p2/170307/upload_8eg778435c1jjhc4hkf2leiclalg2_640x900.jpg_320x999.jpg",
          "h": 416
        },
        "type": 2,
        "sale": 33,
        "title": "【条纹链条包】波浪纹包包新款韩版单肩包斜挎包",
        "cfav": 2699,
        "price": "￥116.25",
        "ptpC": "_mb_mls_0_wap-search_noab-noab",
        "lefttop_taglist": [],
        "showLarge": {
          "img": "http://s2.mogucdn.com/p2/170307/upload_8eg778435c1jjhc4hkf2leiclalg2_640x900.jpg_560x999.jpg",
          "w": 560,
          "h": 788
        },
        "leftbottom_taglist": []
      },
      {
        "orgPrice": "￥156.25",
        "acm": "3.ms.2_4_1h4auyi.0.24470-25176.05NORqhIsBsQq.t_0-lc_17",
        "iid": "1h4auyi",
        "link": "http://item.meilishuo.com/h5/detail/1h4auyi?acm=3.ms.2_4_1h4auyi.0.24470-25176.05NORqhIsBsQq.t_0-lc_17",
        "clientUrl": "http://item.meilishuo.com/h5/detail/1h4auyi?acm=3.ms.2_4_1h4auyi.0.24470-25176.05NORqhIsBsQq.t_0-lc_17",
        "itemType": 4,
        "popularStar": null,
        "cparam": null,
        "itemMarks": "135 107",
        "show": {
          "w": 320,
          "img": "http://s2.mogucdn.com/p2/170307/upload_8ebl0fff1jjh643ka5kbc111iegg8_640x900.jpg_320x999.jpg",
          "h": 416
        },
        "type": 2,
        "sale": 4,
        "title": "2017新款时尚女包小盒子包包锁扣复古小方包斜挎包小箱子包",
        "cfav": 985,
        "price": "￥156.25",
        "ptpC": "_mb_mls_0_wap-search_noab-noab",
        "lefttop_taglist": [],
        "showLarge": {
          "img": "http://s2.mogucdn.com/p2/170307/upload_8ebl0fff1jjh643ka5kbc111iegg8_640x900.jpg_560x999.jpg",
          "w": 560,
          "h": 788
        },
        "leftbottom_taglist": []
      },
      {
        "orgPrice": "￥648.00",
        "acm": "3.ms.2_4_1gknoqg.0.8239-25176.05NORqhIsBsQq.t_0-lc_17",
        "iid": "1gknoqg",
        "link": "http://item.meilishuo.com/h5/detail/1gknoqg?acm=3.ms.2_4_1gknoqg.0.8239-25176.05NORqhIsBsQq.t_0-lc_17",
        "clientUrl": "http://item.meilishuo.com/h5/detail/1gknoqg?acm=3.ms.2_4_1gknoqg.0.8239-25176.05NORqhIsBsQq.t_0-lc_17",
        "itemType": 1,
        "popularStar": null,
        "cparam": null,
        "itemMarks": "98 107",
        "show": {
          "w": 320,
          "img": "http://s2.mogucdn.com/p1/160626/1339505863_ifqweobwg43domrwhezdambqgyyde_640x960.jpg_320x999.jpg",
          "h": 416
        },
        "type": 2,
        "sale": 1,
        "title": "贝壳包女包 麦包包新款可爱春夏季百搭斜挎定型包 手提包女小",
        "cfav": 122,
        "price": "￥181.44",
        "ptpC": "_mb_mls_0_wap-search_noab-noab",
        "lefttop_taglist": [
          {
            "img": "http://s18.mogucdn.com/b7/avatar/160520/1y0mpt_ie4tqodbgrrdcnlbhazdambqgqyde_50x54.jpg",
            "w": 50,
            "h": 54
          }
        ],
        "showLarge": {
          "img": "http://s2.mogucdn.com/p1/160626/1339505863_ifqweobwg43domrwhezdambqgyyde_640x960.jpg_560x999.jpg",
          "w": 560,
          "h": 840
        },
        "leftbottom_taglist": []
      },
      {
        "orgPrice": "￥209.00",
        "acm": "3.ms.2_4_1h4qvci.0.8239-25176.05NORqhIsBsQq.t_0-lc_17",
        "iid": "1h4qvci",
        "link": "http://item.meilishuo.com/h5/detail/1h4qvci?acm=3.ms.2_4_1h4qvci.0.8239-25176.05NORqhIsBsQq.t_0-lc_17",
        "clientUrl": "http://item.meilishuo.com/h5/detail/1h4qvci?acm=3.ms.2_4_1h4qvci.0.8239-25176.05NORqhIsBsQq.t_0-lc_17",
        "itemType": 1,
        "popularStar": null,
        "cparam": null,
        "itemMarks": "",
        "show": {
          "w": 320,
          "img": "http://s2.mogucdn.com/p2/170221/869099060_0jidd14cc340956e7hlk571g16e9g_640x960.jpg_320x999.jpg",
          "h": 416
        },
        "type": 2,
        "sale": 0,
        "title": "不莱玫2017新款女包韩版斜跨包时尚机车包迷你单肩包小包包",
        "cfav": 7,
        "price": "￥209.00",
        "ptpC": "_mb_mls_0_wap-search_noab-noab",
        "lefttop_taglist": [
          {
            "img": "http://s18.mogucdn.com/b7/avatar/160520/1y0mpt_ie4tqodbgrrdcnlbhazdambqgqyde_50x54.jpg",
            "w": 50,
            "h": 54
          }
        ],
        "showLarge": {
          "img": "http://s2.mogucdn.com/p2/170221/869099060_0jidd14cc340956e7hlk571g16e9g_640x960.jpg_560x999.jpg",
          "w": 560,
          "h": 840
        },
        "leftbottom_taglist": []
      },
      {
        "orgPrice": "￥469.00",
        "acm": "3.ms.2_4_1gkmayk.0.8239-25176.05NORqhIsBsQq.t_0-lc_17",
        "iid": "1gkmayk",
        "link": "http://item.meilishuo.com/h5/detail/1gkmayk?acm=3.ms.2_4_1gkmayk.0.8239-25176.05NORqhIsBsQq.t_0-lc_17",
        "clientUrl": "http://item.meilishuo.com/h5/detail/1gkmayk?acm=3.ms.2_4_1gkmayk.0.8239-25176.05NORqhIsBsQq.t_0-lc_17",
        "itemType": 1,
        "popularStar": null,
        "cparam": null,
        "itemMarks": "98 107",
        "show": {
          "w": 320,
          "img": "http://s2.mogucdn.com/p2/161213/1339505863_8ciaekl91a744gd03k257jdkal205_640x960.jpg_320x999.jpg",
          "h": 416
        },
        "type": 2,
        "sale": 0,
        "title": "麦包包日韩新款时尚小香风菱格锁扣链条包女士包包单肩女包斜挎包",
        "cfav": 75,
        "price": "￥117.25",
        "ptpC": "_mb_mls_0_wap-search_noab-noab",
        "lefttop_taglist": [
          {
            "img": "http://s18.mogucdn.com/b7/avatar/160520/1y0mpt_ie4tqodbgrrdcnlbhazdambqgqyde_50x54.jpg",
            "w": 50,
            "h": 54
          }
        ],
        "showLarge": {
          "img": "http://s2.mogucdn.com/p2/161213/1339505863_8ciaekl91a744gd03k257jdkal205_640x960.jpg_560x999.jpg",
          "w": 560,
          "h": 840
        },
        "leftbottom_taglist": []
      },
      {
        "orgPrice": "￥73.75",
        "acm": "3.ms.2_4_1h5lvj4.0.24470-25176.05NORqhIsBsQq.t_0-lc_17",
        "iid": "1h5lvj4",
        "link": "http://item.meilishuo.com/h5/detail/1h5lvj4?acm=3.ms.2_4_1h5lvj4.0.24470-25176.05NORqhIsBsQq.t_0-lc_17",
        "clientUrl": "http://item.meilishuo.com/h5/detail/1h5lvj4?acm=3.ms.2_4_1h5lvj4.0.24470-25176.05NORqhIsBsQq.t_0-lc_17",
        "itemType": 4,
        "popularStar": null,
        "cparam": null,
        "itemMarks": "107 135",
        "show": {
          "w": 320,
          "img": "http://s2.mogucdn.com/p2/170216/upload_69ee438g6hefilj8j71lb3i52jj5j_640x900.jpg_320x999.jpg",
          "h": 416
        },
        "type": 2,
        "sale": 29,
        "title": "信封手提包翻毛皮小包复古简约斜跨包单肩包链条包包",
        "cfav": 1233,
        "price": "￥73.75",
        "ptpC": "_mb_mls_0_wap-search_noab-noab",
        "lefttop_taglist": [],
        "showLarge": {
          "img": "http://s2.mogucdn.com/p2/170216/upload_69ee438g6hefilj8j71lb3i52jj5j_640x900.jpg_560x999.jpg",
          "w": 560,
          "h": 788
        },
        "leftbottom_taglist": []
      },
      {
        "orgPrice": "￥179.90",
        "acm": "3.ms.2_1_1h6h66k.1.5865-25176.05NORqhIsBsQq.t_0-lc_17-c_1_17_182851411_0_3_0-c1_",
        "iid": "1h6h66k",
        "link": "http://item.meilishuo.com/h5/detail/1h6h66k?acm=3.ms.2_1_1h6h66k.1.5865-25176.05NORqhIsBsQq.t_0-lc_17-c_1_17_182851411_0_3_0-c1_&cparam=MTQ5MzAzNzM1OV8xNXV1ejIyXzQ3ZjkxOWJlOTM4YTFiNjBlZjMwYjdiODhlNmRiMjc4XzE3XzJfMTgyODUxNDExXzAuOTEzOF8wXzNfMV8xMzVfMF8w",
        "clientUrl": "http://item.meilishuo.com/h5/detail/1h6h66k?acm=3.ms.2_1_1h6h66k.1.5865-25176.05NORqhIsBsQq.t_0-lc_17-c_1_17_182851411_0_3_0-c1_&cparam=MTQ5MzAzNzM1OV8xNXV1ejIyXzQ3ZjkxOWJlOTM4YTFiNjBlZjMwYjdiODhlNmRiMjc4XzE3XzJfMTgyODUxNDExXzAuOTEzOF8wXzNfMV8xMzVfMF8w",
        "itemType": 3,
        "popularStar": null,
        "cparam": "MTQ5MzAzNzM1OV8xNXV1ejIyXzQ3ZjkxOWJlOTM4YTFiNjBlZjMwYjdiODhlNmRiMjc4XzE3XzJfMTgyODUxNDExXzAuOTEzOF8wXzNfMV8xMzVfMF8w",
        "itemMarks": "",
        "show": {
          "w": 320,
          "img": "http://s2.mogucdn.com/p2/170316/1324219527_4l7496fjbc4afi2ij75g88bl9djl0_640x842.jpg_320x999.jpg",
          "h": 416
        },
        "type": 2,
        "sale": "34",
        "title": "单肩包欧美时尚个性口红插扣小方包2017新款链条包斜挎小包包",
        "cfav": "192",
        "price": "￥89.95",
        "ptpC": "_mb_mls_0_wap-search_noab-noab",
        "lefttop_taglist": [],
        "showLarge": {
          "img": "http://s2.mogucdn.com/p2/170316/1324219527_4l7496fjbc4afi2ij75g88bl9djl0_640x842.jpg_560x999.jpg",
          "w": 560,
          "h": 737
        },
        "leftbottom_taglist": []
      },
      {
        "orgPrice": "￥178.00",
        "acm": "3.ms.2_1_1fvndwa.1.5865-25176.05NORqhIsBsQq.t_0-lc_17-c_1_17_177082209_0_4_0-c1_",
        "iid": "1fvndwa",
        "link": "http://item.meilishuo.com/h5/detail/1fvndwa?acm=3.ms.2_1_1fvndwa.1.5865-25176.05NORqhIsBsQq.t_0-lc_17-c_1_17_177082209_0_4_0-c1_&cparam=MTQ5MzAzNzM1OV8xNmhndHgwXzVjMTE4ZGM4NTZmYjdjZGIwYmY5MjdkYTNjODBjNWQ2XzE3XzNfMTc3MDgyMjA5XzAuOTkyNF8wXzRfMV8yODdfMF8w",
        "clientUrl": "http://item.meilishuo.com/h5/detail/1fvndwa?acm=3.ms.2_1_1fvndwa.1.5865-25176.05NORqhIsBsQq.t_0-lc_17-c_1_17_177082209_0_4_0-c1_&cparam=MTQ5MzAzNzM1OV8xNmhndHgwXzVjMTE4ZGM4NTZmYjdjZGIwYmY5MjdkYTNjODBjNWQ2XzE3XzNfMTc3MDgyMjA5XzAuOTkyNF8wXzRfMV8yODdfMF8w",
        "itemType": 3,
        "popularStar": null,
        "cparam": "MTQ5MzAzNzM1OV8xNmhndHgwXzVjMTE4ZGM4NTZmYjdjZGIwYmY5MjdkYTNjODBjNWQ2XzE3XzNfMTc3MDgyMjA5XzAuOTkyNF8wXzRfMV8yODdfMF8w",
        "itemMarks": "98 82 107",
        "show": {
          "w": 320,
          "img": "http://d01.res.meilishuo.net/pic/_o/82/ab/be795b79ccccb6de8ec274b88904_640_842.cj.jpg_5250b736_s1_320_999.jpg",
          "h": 416
        },
        "type": 2,
        "sale": "92",
        "title": "韩版复古夹子三层单肩包",
        "cfav": "4374",
        "price": "￥89.00",
        "ptpC": "_mb_mls_0_wap-search_noab-noab",
        "lefttop_taglist": [],
        "showLarge": {
          "img": "http://d01.res.meilishuo.net/pic/_o/82/ab/be795b79ccccb6de8ec274b88904_640_842.cj.jpg_cf56909f_s1_560_999.jpg",
          "w": 560,
          "h": 737
        },
        "leftbottom_taglist": []
      },
      {
        "orgPrice": "￥58.75",
        "acm": "3.ms.2_4_1kam7fm.0.24470-25176.05NORqhIsBsQq.t_0-lc_17",
        "iid": "1kam7fm",
        "link": "http://item.meilishuo.com/h5/detail/1kam7fm?acm=3.ms.2_4_1kam7fm.0.24470-25176.05NORqhIsBsQq.t_0-lc_17",
        "clientUrl": "http://item.meilishuo.com/h5/detail/1kam7fm?acm=3.ms.2_4_1kam7fm.0.24470-25176.05NORqhIsBsQq.t_0-lc_17",
        "itemType": 4,
        "popularStar": null,
        "cparam": null,
        "itemMarks": "135",
        "show": {
          "w": 320,
          "img": "http://s2.mogucdn.com/p2/170411/upload_3ia09e880glajkae4keeg0d7jhae2_640x900.jpg_320x999.jpg",
          "h": 416
        },
        "type": 2,
        "sale": 7,
        "title": "2017夏季新款韩版铆钉单肩包百搭斜挎包休闲手提包小包包",
        "cfav": 486,
        "price": "￥58.75",
        "ptpC": "_mb_mls_0_wap-search_noab-noab",
        "lefttop_taglist": [],
        "showLarge": {
          "img": "http://s2.mogucdn.com/p2/170411/upload_3ia09e880glajkae4keeg0d7jhae2_640x900.jpg_560x999.jpg",
          "w": 560,
          "h": 788
        },
        "leftbottom_taglist": []
      },
      {
        "orgPrice": "￥118.75",
        "acm": "3.ms.2_4_1h4j26u.0.24470-25176.05NORqhIsBsQq.t_0-lc_17",
        "iid": "1h4j26u",
        "link": "http://item.meilishuo.com/h5/detail/1h4j26u?acm=3.ms.2_4_1h4j26u.0.24470-25176.05NORqhIsBsQq.t_0-lc_17",
        "clientUrl": "http://item.meilishuo.com/h5/detail/1h4j26u?acm=3.ms.2_4_1h4j26u.0.24470-25176.05NORqhIsBsQq.t_0-lc_17",
        "itemType": 4,
        "popularStar": null,
        "cparam": null,
        "itemMarks": "135",
        "show": {
          "w": 320,
          "img": "http://s2.mogucdn.com/p2/170307/upload_4h31d263a4jjfbg791bc2c2ibba20_640x900.jpg_320x999.jpg",
          "h": 416
        },
        "type": 2,
        "sale": 21,
        "title": "定制皮扣包包2017春季新款欧美单肩包复古锁扣斜跨手提女包潮",
        "cfav": 1106,
        "price": "￥118.75",
        "ptpC": "_mb_mls_0_wap-search_noab-noab",
        "lefttop_taglist": [],
        "showLarge": {
          "img": "http://s17.mogucdn.com/p2/170307/upload_4h31d263a4jjfbg791bc2c2ibba20_640x900.jpg_560x999.jpg",
          "w": 560,
          "h": 788
        },
        "leftbottom_taglist": []
      },
      {
        "orgPrice": "￥71.25",
        "acm": "3.ms.2_4_1h4xapu.0.24470-25176.05NORqhIsBsQq.t_0-lc_17",
        "iid": "1h4xapu",
        "link": "http://item.meilishuo.com/h5/detail/1h4xapu?acm=3.ms.2_4_1h4xapu.0.24470-25176.05NORqhIsBsQq.t_0-lc_17",
        "clientUrl": "http://item.meilishuo.com/h5/detail/1h4xapu?acm=3.ms.2_4_1h4xapu.0.24470-25176.05NORqhIsBsQq.t_0-lc_17",
        "itemType": 4,
        "popularStar": null,
        "cparam": null,
        "itemMarks": "135 107",
        "show": {
          "w": 320,
          "img": "http://s2.mogucdn.com/p2/170213/upload_5g6kcbe5gf5fhabkkhaj87k9cbd3k_640x900.jpg_320x999.jpg",
          "h": 416
        },
        "type": 2,
        "sale": 2,
        "title": "女包包2017春夏韩版新款小包包百搭时尚休闲双面单肩斜挎包潮",
        "cfav": 214,
        "price": "￥71.25",
        "ptpC": "_mb_mls_0_wap-search_noab-noab",
        "lefttop_taglist": [],
        "showLarge": {
          "img": "http://s2.mogucdn.com/p2/170213/upload_5g6kcbe5gf5fhabkkhaj87k9cbd3k_640x900.jpg_560x999.jpg",
          "w": 560,
          "h": 788
        },
        "leftbottom_taglist": []
      },
      {
        "orgPrice": "￥137.50",
        "acm": "3.ms.2_4_1h4dmly.0.24470-25176.05NORqhIsBsQq.t_0-lc_17",
        "iid": "1h4dmly",
        "link": "http://item.meilishuo.com/h5/detail/1h4dmly?acm=3.ms.2_4_1h4dmly.0.24470-25176.05NORqhIsBsQq.t_0-lc_17",
        "clientUrl": "http://item.meilishuo.com/h5/detail/1h4dmly?acm=3.ms.2_4_1h4dmly.0.24470-25176.05NORqhIsBsQq.t_0-lc_17",
        "itemType": 4,
        "popularStar": null,
        "cparam": null,
        "itemMarks": "107 135",
        "show": {
          "w": 320,
          "img": "http://s2.mogucdn.com/p2/170207/upload_2e1e1ej6ifi9l428l9j885gejdec6_640x900.jpg_320x999.jpg",
          "h": 416
        },
        "type": 2,
        "sale": 5,
        "title": "麦包包女士包包新款时尚百搭女包单肩斜挎包小包复古马鞍包",
        "cfav": 579,
        "price": "￥137.50",
        "ptpC": "_mb_mls_0_wap-search_noab-noab",
        "lefttop_taglist": [],
        "showLarge": {
          "img": "http://s2.mogucdn.com/p2/170207/upload_2e1e1ej6ifi9l428l9j885gejdec6_640x900.jpg_560x999.jpg",
          "w": 560,
          "h": 788
        },
        "leftbottom_taglist": []
      },
      {
        "orgPrice": "￥372.50",
        "acm": "3.ms.2_4_1gk611m.0.8239-25176.05NORqhIsBsQq.t_0-lc_17",
        "iid": "1gk611m",
        "link": "http://item.meilishuo.com/h5/detail/1gk611m?acm=3.ms.2_4_1gk611m.0.8239-25176.05NORqhIsBsQq.t_0-lc_17",
        "clientUrl": "http://item.meilishuo.com/h5/detail/1gk611m?acm=3.ms.2_4_1gk611m.0.8239-25176.05NORqhIsBsQq.t_0-lc_17",
        "itemType": 1,
        "popularStar": null,
        "cparam": null,
        "itemMarks": "98 107",
        "show": {
          "w": 320,
          "img": "http://s2.mogucdn.com/p1/160608/871729094_ie4tgnbxmjqtqnrqhezdambqgqyde_640x832.jpg_320x999.jpg",
          "h": 416
        },
        "type": 2,
        "sale": 1,
        "title": "香港Artmi小香风菱格斜挎包简约甜美淑女链条包包单肩小包",
        "cfav": 70,
        "price": "￥149.00",
        "ptpC": "_mb_mls_0_wap-search_noab-noab",
        "lefttop_taglist": [
          {
            "img": "http://s18.mogucdn.com/b7/avatar/160520/1y0mpt_ie4tqodbgrrdcnlbhazdambqgqyde_50x54.jpg",
            "w": 50,
            "h": 54
          }
        ],
        "showLarge": {
          "img": "http://s2.mogucdn.com/p1/160608/871729094_ie4tgnbxmjqtqnrqhezdambqgqyde_640x832.jpg_560x999.jpg",
          "w": 560,
          "h": 728
        },
        "leftbottom_taglist": []
      },
      {
        "orgPrice": "￥1418.00",
        "acm": "3.ms.2_4_1gkx734.0.8239-25176.05NORqhIsBsQq.t_0-lc_17",
        "iid": "1gkx734",
        "link": "http://item.meilishuo.com/h5/detail/1gkx734?acm=3.ms.2_4_1gkx734.0.8239-25176.05NORqhIsBsQq.t_0-lc_17",
        "clientUrl": "http://item.meilishuo.com/h5/detail/1gkx734?acm=3.ms.2_4_1gkx734.0.8239-25176.05NORqhIsBsQq.t_0-lc_17",
        "itemType": 1,
        "popularStar": null,
        "cparam": null,
        "itemMarks": "98 107",
        "show": {
          "w": 320,
          "img": "http://s2.mogucdn.com/p1/160711/1339505863_ie4genlfmm4wimlchezdambqgiyde_640x960.jpg_320x999.jpg",
          "h": 416
        },
        "type": 2,
        "sale": 1,
        "title": "麦包包DUDU 2017春夏新款经典链条包羊皮菱格包包斜挎包",
        "cfav": 27,
        "price": "￥297.78",
        "ptpC": "_mb_mls_0_wap-search_noab-noab",
        "lefttop_taglist": [
          {
            "img": "http://s18.mogucdn.com/b7/avatar/160520/1y0mpt_ie4tqodbgrrdcnlbhazdambqgqyde_50x54.jpg",
            "w": 50,
            "h": 54
          }
        ],
        "showLarge": {
          "img": "http://s2.mogucdn.com/p1/160711/1339505863_ie4genlfmm4wimlchezdambqgiyde_640x960.jpg_560x999.jpg",
          "w": 560,
          "h": 840
        },
        "leftbottom_taglist": []
      },
      {
        "orgPrice": "￥658.00",
        "acm": "3.ms.2_4_1gkn22a.0.8239-25176.05NORqhIsBsQq.t_0-lc_17",
        "iid": "1gkn22a",
        "link": "http://item.meilishuo.com/h5/detail/1gkn22a?acm=3.ms.2_4_1gkn22a.0.8239-25176.05NORqhIsBsQq.t_0-lc_17",
        "clientUrl": "http://item.meilishuo.com/h5/detail/1gkn22a?acm=3.ms.2_4_1gkn22a.0.8239-25176.05NORqhIsBsQq.t_0-lc_17",
        "itemType": 1,
        "popularStar": null,
        "cparam": null,
        "itemMarks": "98 107",
        "show": {
          "w": 320,
          "img": "http://s2.mogucdn.com/p2/161026/1339505863_86ef1i2dk0gk7i36k1jl1c53kj12b_640x960.jpg_320x999.jpg",
          "h": 416
        },
        "type": 2,
        "sale": 1,
        "title": "麦包包17新款春夏小包包斜挎包夏款手提包女士迷你斜跨小包女包",
        "cfav": 108,
        "price": "￥177.66",
        "ptpC": "_mb_mls_0_wap-search_noab-noab",
        "lefttop_taglist": [
          {
            "img": "http://s18.mogucdn.com/b7/avatar/160520/1y0mpt_ie4tqodbgrrdcnlbhazdambqgqyde_50x54.jpg",
            "w": 50,
            "h": 54
          }
        ],
        "showLarge": {
          "img": "http://s2.mogucdn.com/p2/161026/1339505863_86ef1i2dk0gk7i36k1jl1c53kj12b_640x960.jpg_560x999.jpg",
          "w": 560,
          "h": 840
        },
        "leftbottom_taglist": []
      },
      {
        "orgPrice": "￥50.00",
        "acm": "3.ms.2_4_1kaosre.0.24470-25176.05NORqhIsBsQq.t_0-lc_17",
        "iid": "1kaosre",
        "link": "http://item.meilishuo.com/h5/detail/1kaosre?acm=3.ms.2_4_1kaosre.0.24470-25176.05NORqhIsBsQq.t_0-lc_17",
        "clientUrl": "http://item.meilishuo.com/h5/detail/1kaosre?acm=3.ms.2_4_1kaosre.0.24470-25176.05NORqhIsBsQq.t_0-lc_17",
        "itemType": 4,
        "popularStar": null,
        "cparam": null,
        "itemMarks": "135",
        "show": {
          "w": 320,
          "img": "http://s2.mogucdn.com/p2/170421/upload_7lhkg1h5ll5fc53gf4hdj99bl96il_640x900.jpg_320x999.jpg",
          "h": 416
        },
        "type": 2,
        "sale": 0,
        "title": "2017夏季新款包包斜挎包甜美花朵迷你小包休闲百搭链条单肩包",
        "cfav": 492,
        "price": "￥50.00",
        "ptpC": "_mb_mls_0_wap-search_noab-noab",
        "lefttop_taglist": [],
        "showLarge": {
          "img": "http://s2.mogucdn.com/p2/170421/upload_7lhkg1h5ll5fc53gf4hdj99bl96il_640x900.jpg_560x999.jpg",
          "w": 560,
          "h": 788
        },
        "leftbottom_taglist": []
      },
      {
        "orgPrice": "￥293.00",
        "acm": "3.ms.2_1_1kab392.1.5865-25176.05NORqhIsBsQq.t_0-lc_17-c_1_17_196067870_0_5_0-c1_",
        "iid": "1kab392",
        "link": "http://item.meilishuo.com/h5/detail/1kab392?acm=3.ms.2_1_1kab392.1.5865-25176.05NORqhIsBsQq.t_0-lc_17-c_1_17_196067870_0_5_0-c1_&cparam=MTQ5MzAzNzM1OV8xNjh6d2RzX2UxZTY3Njc1MzkwYzFhZWE4NGM0YWQ0Y2QxMjc2OWI3XzE3XzRfMTk2MDY3ODcwXzAuOTI5OV8wXzVfMV81MjFfMF8w",
        "clientUrl": "http://item.meilishuo.com/h5/detail/1kab392?acm=3.ms.2_1_1kab392.1.5865-25176.05NORqhIsBsQq.t_0-lc_17-c_1_17_196067870_0_5_0-c1_&cparam=MTQ5MzAzNzM1OV8xNjh6d2RzX2UxZTY3Njc1MzkwYzFhZWE4NGM0YWQ0Y2QxMjc2OWI3XzE3XzRfMTk2MDY3ODcwXzAuOTI5OV8wXzVfMV81MjFfMF8w",
        "itemType": 3,
        "popularStar": null,
        "cparam": "MTQ5MzAzNzM1OV8xNjh6d2RzX2UxZTY3Njc1MzkwYzFhZWE4NGM0YWQ0Y2QxMjc2OWI3XzE3XzRfMTk2MDY3ODcwXzAuOTI5OV8wXzVfMV81MjFfMF8w",
        "itemMarks": "62",
        "show": {
          "w": 320,
          "img": "http://s2.mogucdn.com/mlcdn/c45406/170415_8b7h992h587jciejfehic7210bhdd_640x832.jpg_320x999.jpg",
          "h": 416
        },
        "type": 2,
        "sale": "0",
        "title": "杨幂娜扎同款女包17新款撞色锁扣包欧美百搭斜挎包时尚单肩包",
        "cfav": "4",
        "price": "￥87.90",
        "ptpC": "_mb_mls_0_wap-search_noab-noab",
        "lefttop_taglist": [],
        "showLarge": {
          "img": "http://s2.mogucdn.com/mlcdn/c45406/170415_8b7h992h587jciejfehic7210bhdd_640x832.jpg_560x999.jpg",
          "w": 560,
          "h": 728
        },
        "leftbottom_taglist": []
      },
      {
        "orgPrice": "￥179.90",
        "acm": "3.ms.2_1_1h6vvye.1.5865-25176.05NORqhIsBsQq.t_0-lc_17-c_1_17_188954428_0_6_0-c1_",
        "iid": "1h6vvye",
        "link": "http://item.meilishuo.com/h5/detail/1h6vvye?acm=3.ms.2_1_1h6vvye.1.5865-25176.05NORqhIsBsQq.t_0-lc_17-c_1_17_188954428_0_6_0-c1_&cparam=MTQ5MzAzNzM1OV8xMWtfM2U1N2E1Y2RlOGU1M2NjOWUzNjJkZjkzNjU1MGIzZTJfMTdfNV8xODg5NTQ0MjhfMF8wXzZfMV8xMzVfMF8w",
        "clientUrl": "http://item.meilishuo.com/h5/detail/1h6vvye?acm=3.ms.2_1_1h6vvye.1.5865-25176.05NORqhIsBsQq.t_0-lc_17-c_1_17_188954428_0_6_0-c1_&cparam=MTQ5MzAzNzM1OV8xMWtfM2U1N2E1Y2RlOGU1M2NjOWUzNjJkZjkzNjU1MGIzZTJfMTdfNV8xODg5NTQ0MjhfMF8wXzZfMV8xMzVfMF8w",
        "itemType": 3,
        "popularStar": null,
        "cparam": "MTQ5MzAzNzM1OV8xMWtfM2U1N2E1Y2RlOGU1M2NjOWUzNjJkZjkzNjU1MGIzZTJfMTdfNV8xODg5NTQ0MjhfMF8wXzZfMV8xMzVfMF8w",
        "itemMarks": "",
        "show": {
          "w": 320,
          "img": "http://s2.mogucdn.com/mlcdn/c45406/170327_5683e5119k6j2jjbd409c61c45d1c_640x832.jpg_320x999.jpg",
          "h": 416
        },
        "type": 2,
        "sale": "60",
        "title": "新款单肩包斜挎包手提包女小包欧美时尚撞色链条包小方包简约",
        "cfav": "268",
        "price": "￥89.95",
        "ptpC": "_mb_mls_0_wap-search_noab-noab",
        "lefttop_taglist": [],
        "showLarge": {
          "img": "http://s2.mogucdn.com/mlcdn/c45406/170327_5683e5119k6j2jjbd409c61c45d1c_640x832.jpg_560x999.jpg",
          "w": 560,
          "h": 728
        },
        "leftbottom_taglist": []
      },
      {
        "orgPrice": "￥156.25",
        "acm": "3.ms.2_4_1h4c0qk.0.24470-25176.05NORqhIsBsQq.t_0-lc_17",
        "iid": "1h4c0qk",
        "link": "http://item.meilishuo.com/h5/detail/1h4c0qk?acm=3.ms.2_4_1h4c0qk.0.24470-25176.05NORqhIsBsQq.t_0-lc_17",
        "clientUrl": "http://item.meilishuo.com/h5/detail/1h4c0qk?acm=3.ms.2_4_1h4c0qk.0.24470-25176.05NORqhIsBsQq.t_0-lc_17",
        "itemType": 4,
        "popularStar": null,
        "cparam": null,
        "itemMarks": "107 135",
        "show": {
          "w": 320,
          "img": "http://s2.mogucdn.com/p2/170207/upload_395hlb9fjl3kkd29ee6dg63e2783e_640x900.jpg_320x999.jpg",
          "h": 416
        },
        "type": 2,
        "sale": 2,
        "title": "【麦包包】2017春夏新款小清新撞色手提单肩女包",
        "cfav": 269,
        "price": "￥156.25",
        "ptpC": "_mb_mls_0_wap-search_noab-noab",
        "lefttop_taglist": [],
        "showLarge": {
          "img": "http://s2.mogucdn.com/p2/170207/upload_395hlb9fjl3kkd29ee6dg63e2783e_640x900.jpg_560x999.jpg",
          "w": 560,
          "h": 788
        },
        "leftbottom_taglist": []
      },
      {
        "orgPrice": "￥55.00",
        "acm": "3.ms.2_4_1ka8uzo.0.24470-25176.05NORqhIsBsQq.t_0-lc_17",
        "iid": "1ka8uzo",
        "link": "http://item.meilishuo.com/h5/detail/1ka8uzo?acm=3.ms.2_4_1ka8uzo.0.24470-25176.05NORqhIsBsQq.t_0-lc_17",
        "clientUrl": "http://item.meilishuo.com/h5/detail/1ka8uzo?acm=3.ms.2_4_1ka8uzo.0.24470-25176.05NORqhIsBsQq.t_0-lc_17",
        "itemType": 4,
        "popularStar": null,
        "cparam": null,
        "itemMarks": "107 135",
        "show": {
          "w": 320,
          "img": "http://s2.mogucdn.com/p2/170414/upload_1e1affijkc2glbiigc619c06j1ala_1000x1406.jpg_320x999.jpg",
          "h": 416
        },
        "type": 2,
        "sale": 117,
        "title": "2017新款复古个性锁扣链条小方包时尚潮流单肩斜挎包小包包",
        "cfav": 680,
        "price": "￥55.00",
        "ptpC": "_mb_mls_0_wap-search_noab-noab",
        "lefttop_taglist": [],
        "showLarge": {
          "img": "http://s2.mogucdn.com/p2/170414/upload_1e1affijkc2glbiigc619c06j1ala_1000x1406.jpg_560x999.jpg",
          "w": 560,
          "h": 788
        },
        "leftbottom_taglist": []
      },
      {
        "orgPrice": "￥115.00",
        "acm": "3.ms.2_4_1h5q6ey.0.24470-25176.05NORqhIsBsQq.t_0-lc_17",
        "iid": "1h5q6ey",
        "link": "http://item.meilishuo.com/h5/detail/1h5q6ey?acm=3.ms.2_4_1h5q6ey.0.24470-25176.05NORqhIsBsQq.t_0-lc_17",
        "clientUrl": "http://item.meilishuo.com/h5/detail/1h5q6ey?acm=3.ms.2_4_1h5q6ey.0.24470-25176.05NORqhIsBsQq.t_0-lc_17",
        "itemType": 4,
        "popularStar": null,
        "cparam": null,
        "itemMarks": "135 107",
        "show": {
          "w": 320,
          "img": "http://s2.mogucdn.com/p2/170307/upload_5i0i6058ejf21acg287gfc22ehd59_640x900.jpg_320x999.jpg",
          "h": 416
        },
        "type": 2,
        "sale": 5,
        "title": "回形针包包女2017新款欧美时尚纯色单肩包复古斜跨包小包",
        "cfav": 146,
        "price": "￥115.00",
        "ptpC": "_mb_mls_0_wap-search_noab-noab",
        "lefttop_taglist": [],
        "showLarge": {
          "img": "http://s2.mogucdn.com/p2/170307/upload_5i0i6058ejf21acg287gfc22ehd59_640x900.jpg_560x999.jpg",
          "w": 560,
          "h": 788
        },
        "leftbottom_taglist": []
      },
      {
        "orgPrice": "￥48.75",
        "acm": "3.ms.2_4_1ka1w0w.0.24470-25176.05NORqhIsBsQq.t_0-lc_17",
        "iid": "1ka1w0w",
        "link": "http://item.meilishuo.com/h5/detail/1ka1w0w?acm=3.ms.2_4_1ka1w0w.0.24470-25176.05NORqhIsBsQq.t_0-lc_17",
        "clientUrl": "http://item.meilishuo.com/h5/detail/1ka1w0w?acm=3.ms.2_4_1ka1w0w.0.24470-25176.05NORqhIsBsQq.t_0-lc_17",
        "itemType": 4,
        "popularStar": null,
        "cparam": null,
        "itemMarks": "135 107",
        "show": {
          "w": 320,
          "img": "http://s2.mogucdn.com/p2/170413/upload_70ebj601f350ii0i6c707eei112id_640x900.jpg_320x999.jpg",
          "h": 416
        },
        "type": 2,
        "sale": 53,
        "title": "包包2017夏季新款复古简约果冻手提包女式休闲斜挎小包子母包",
        "cfav": 524,
        "price": "￥48.75",
        "ptpC": "_mb_mls_0_wap-search_noab-noab",
        "lefttop_taglist": [],
        "showLarge": {
          "img": "http://s2.mogucdn.com/p2/170413/upload_70ebj601f350ii0i6c707eei112id_640x900.jpg_560x999.jpg",
          "w": 560,
          "h": 788
        },
        "leftbottom_taglist": []
      }
    ],
    "ptpPartC": "_mb_mls_0_wap-search_noab-noab",
    "filter": {
      "title": "wap图墙",
      "list": [
        {
          "title": "综合",
          "sort": "pop",
          "style": null,
          "fcid": "null",
          "type": "sort"
        },
        {
          "title": "销量",
          "sort": "sell",
          "style": null,
          "fcid": "null",
          "type": "sort"
        },
        {
          "title": "最新",
          "sort": "new",
          "style": null,
          "fcid": "null",
          "type": "sort"
        }
      ]
    }
  }
}